m3u8/__init__.py
m3u8/httpclient.py
m3u8/mixins.py
m3u8/model.py
m3u8/parser.py
m3u8/protocol.py
m3u8/version_matching.py
m3u8/version_matching_rules.py
m3u8-5.3.0.dist-info/LICENSE
m3u8-5.3.0.dist-info/METADATA
m3u8-5.3.0.dist-info/WHEEL
m3u8-5.3.0.dist-info/top_level.txt
m3u8-5.3.0.dist-info/RECORD
