Metadata-Version: 2.1
Name: m3u8
Version: 5.3.0
Summary: Python m3u8 parser
Home-page: https://github.com/globocom/m3u8
Author: Globo.com
License: MIT
Requires-Python: >=3.7
License-File: LICENSE
Requires-Dist: backports-datetime-fromisoformat ; python_version < "3.11"
